impex/__init__.py
impex/impex.py
onedesk/__init__.py
onedesk/auth/__init__.py
onedesk/auth/auth.py
onedesk/automaton/__init__.py
onedesk/automaton/automaton.py
onedesk/category/__init__.py
onedesk/category/category.py
onedesk/client/__init__.py
onedesk/client/client.py
tests/__init__.py
tests/conftest.py
tests/test_util.py
util/__init__.py
util/arguments.py
util/models.py
util/util.py
clicmod-0.7.2.dist-info/METADATA
clicmod-0.7.2.dist-info/WHEEL
clicmod-0.7.2.dist-info/entry_points.txt
clicmod-0.7.2.dist-info/top_level.txt
clicmod-0.7.2.dist-info/RECORD
